compere/__init__.py
compere/cli.py
compere/main.py
compere/modules/__init__.py
compere/modules/comparison.py
compere/modules/database.py
compere/modules/entity.py
compere/modules/mab.py
compere/modules/models.py
compere/modules/rating.py
compere/modules/similarity.py
compere-0.1.0.dist-info/LICENSE
compere-0.1.0.dist-info/METADATA
compere-0.1.0.dist-info/WHEEL
compere-0.1.0.dist-info/entry_points.txt
compere-0.1.0.dist-info/RECORD
