Metadata-Version: 2.3
Name: compere
Version: 0.1.0
Summary: An advanced comparative rating system that leverages Multi-Armed Bandit (MAB) algorithms and Elo ratings to provide fair and efficient entity comparisons.
License: MIT
Author: Dipankar Sarkar
Author-email: me@dipankar.name
Requires-Python: >=3.11,<4.0
Classifier: License :: OSI Approved :: MIT License
Classifier: Programming Language :: Python :: 3
Classifier: Programming Language :: Python :: 3.11
Classifier: Programming Language :: Python :: 3.12
Classifier: Programming Language :: Python :: 3.13
Requires-Dist: PyJWT (>=2.3.0,<3.0.0)
Requires-Dist: click (>=8.0.0,<9.0.0)
Requires-Dist: fastapi (>=0.68.0,<0.69.0)
Requires-Dist: numpy (>=1.21.0,<2.0.0)
Requires-Dist: passlib (>=1.7.4,<2.0.0)
Requires-Dist: python-dotenv (>=0.18.0,<0.19.0)
Requires-Dist: python-jose (>=3.3.0,<4.0.0)
Requires-Dist: scikit-learn (>=1.0.0,<2.0.0)
Requires-Dist: sqlalchemy (>=1.4.0,<2.0.0)
Requires-Dist: uvicorn (>=0.15.0,<0.16.0)
